{
  "getTransactionSummaryByPeriod" : {
    "transaction" : "getTransactionSummaryByPeriod",
    "sampleCount" : 3,
    "errorCount" : 0,
    "errorPct" : 0.0,
    "meanResTime" : 420.6666666666667,
    "minResTime" : 363.0,
    "maxResTime" : 460.0,
    "pct1ResTime" : 460.0,
    "pct2ResTime" : 460.0,
    "pct3ResTime" : 460.0,
    "throughput" : 0.13303179459890913,
    "receivedKBytesPerSec" : 0.16654957097246242,
    "sentKBytesPerSec" : 0.09691574098709592
  },
  "getScoredTransactionSummaryByJournal" : {
    "transaction" : "getScoredTransactionSummaryByJournal",
    "sampleCount" : 3,
    "errorCount" : 0,
    "errorPct" : 0.0,
    "meanResTime" : 602.0,
    "minResTime" : 571.0,
    "maxResTime" : 622.0,
    "pct1ResTime" : 622.0,
    "pct2ResTime" : 622.0,
    "pct3ResTime" : 622.0,
    "throughput" : 0.13198416190057194,
    "receivedKBytesPerSec" : 0.08816129564452266,
    "sentKBytesPerSec" : 0.09241469148702156
  },
  "(Parent) Generic AAI APIs" : {
    "transaction" : "(Parent) Generic AAI APIs",
    "sampleCount" : 3,
    "errorCount" : 0,
    "errorPct" : 0.0,
    "meanResTime" : 1299.6666666666667,
    "minResTime" : 632.0,
    "maxResTime" : 1664.0,
    "pct1ResTime" : 1664.0,
    "pct2ResTime" : 1664.0,
    "pct3ResTime" : 1664.0,
    "throughput" : 0.1278281989006775,
    "receivedKBytesPerSec" : 0.22207652914482934,
    "sentKBytesPerSec" : 0.2770027083599642
  },
  "getLookupList - USER" : {
    "transaction" : "getLookupList - USER",
    "sampleCount" : 3,
    "errorCount" : 0,
    "errorPct" : 0.0,
    "meanResTime" : 266.3333333333333,
    "minResTime" : 234.0,
    "maxResTime" : 286.0,
    "pct1ResTime" : 286.0,
    "pct2ResTime" : 286.0,
    "pct3ResTime" : 286.0,
    "throughput" : 0.1340422679951745,
    "receivedKBytesPerSec" : 0.06531942551717974,
    "sentKBytesPerSec" : 0.08364551684464501
  },
  "(Parent) Collab Login" : {
    "transaction" : "(Parent) Collab Login",
    "sampleCount" : 1,
    "errorCount" : 0,
    "errorPct" : 0.0,
    "meanResTime" : 1573.0,
    "minResTime" : 1573.0,
    "maxResTime" : 1573.0,
    "pct1ResTime" : 1573.0,
    "pct2ResTime" : 1573.0,
    "pct3ResTime" : 1573.0,
    "throughput" : 0.6357279084551812,
    "receivedKBytesPerSec" : 4.767959313413859,
    "sentKBytesPerSec" : 1.0597534567705023
  },
  "Login_111 /qa-ihub-clean/CWCoreService/restricted/SessionService.svc/Login" : {
    "transaction" : "Login_111 /qa-ihub-clean/CWCoreService/restricted/SessionService.svc/Login",
    "sampleCount" : 1,
    "errorCount" : 0,
    "errorPct" : 0.0,
    "meanResTime" : 1573.0,
    "minResTime" : 1573.0,
    "maxResTime" : 1573.0,
    "pct1ResTime" : 1573.0,
    "pct2ResTime" : 1573.0,
    "pct3ResTime" : 1573.0,
    "throughput" : 0.6357279084551812,
    "receivedKBytesPerSec" : 4.767959313413859,
    "sentKBytesPerSec" : 1.0597534567705023
  },
  "getQueryList" : {
    "transaction" : "getQueryList",
    "sampleCount" : 3,
    "errorCount" : 0,
    "errorPct" : 0.0,
    "meanResTime" : 163.0,
    "minResTime" : 141.0,
    "maxResTime" : 194.0,
    "pct1ResTime" : 194.0,
    "pct2ResTime" : 194.0,
    "pct3ResTime" : 194.0,
    "throughput" : 0.13451105232479937,
    "receivedKBytesPerSec" : 0.5146186191319553,
    "sentKBytesPerSec" : 0.08065408801506524
  },
  "getAppInfo" : {
    "transaction" : "getAppInfo",
    "sampleCount" : 3,
    "errorCount" : 0,
    "errorPct" : 0.0,
    "meanResTime" : 146.66666666666669,
    "minResTime" : 24.0,
    "maxResTime" : 386.0,
    "pct1ResTime" : 386.0,
    "pct2ResTime" : 386.0,
    "pct3ResTime" : 386.0,
    "throughput" : 0.13340448239060834,
    "receivedKBytesPerSec" : 0.03752001067235859,
    "sentKBytesPerSec" : 0.06969863093649947
  },
  "getLatestDataset" : {
    "transaction" : "getLatestDataset",
    "sampleCount" : 3,
    "errorCount" : 0,
    "errorPct" : 0.0,
    "meanResTime" : 58.0,
    "minResTime" : 54.0,
    "maxResTime" : 62.0,
    "pct1ResTime" : 62.0,
    "pct2ResTime" : 62.0,
    "pct3ResTime" : 62.0,
    "throughput" : 0.1331853496115427,
    "receivedKBytesPerSec" : 0.054106548279689234,
    "sentKBytesPerSec" : 0.07036452552719201
  },
  "getLoginInfo" : {
    "transaction" : "getLoginInfo",
    "sampleCount" : 3,
    "errorCount" : 0,
    "errorPct" : 0.0,
    "meanResTime" : 932.0,
    "minResTime" : 512.0,
    "maxResTime" : 1473.0,
    "pct1ResTime" : 1473.0,
    "pct2ResTime" : 1473.0,
    "pct3ResTime" : 1473.0,
    "throughput" : 0.13265531726730045,
    "receivedKBytesPerSec" : 0.07099132213132876,
    "sentKBytesPerSec" : 0.0721572380057484
  },
  "getScoredTransactionList" : {
    "transaction" : "getScoredTransactionList",
    "sampleCount" : 3,
    "errorCount" : 0,
    "errorPct" : 0.0,
    "meanResTime" : 295.6666666666667,
    "minResTime" : 272.0,
    "maxResTime" : 312.0,
    "pct1ResTime" : 312.0,
    "pct2ResTime" : 312.0,
    "pct3ResTime" : 312.0,
    "throughput" : 0.13385686239514547,
    "receivedKBytesPerSec" : 0.12353001461270749,
    "sentKBytesPerSec" : 0.09228803208102802
  },
  "getLookupList - ACCOUNT" : {
    "transaction" : "getLookupList - ACCOUNT",
    "sampleCount" : 3,
    "errorCount" : 0,
    "errorPct" : 0.0,
    "meanResTime" : 161.66666666666666,
    "minResTime" : 138.0,
    "maxResTime" : 190.0,
    "pct1ResTime" : 190.0,
    "pct2ResTime" : 190.0,
    "pct3ResTime" : 190.0,
    "throughput" : 0.1347648353622928,
    "receivedKBytesPerSec" : 0.07396273190782085,
    "sentKBytesPerSec" : 0.08449123467049999
  },
  "getAllSliceStatuses" : {
    "transaction" : "getAllSliceStatuses",
    "sampleCount" : 3,
    "errorCount" : 0,
    "errorPct" : 0.0,
    "meanResTime" : 204.33333333333334,
    "minResTime" : 161.0,
    "maxResTime" : 226.0,
    "pct1ResTime" : 226.0,
    "pct2ResTime" : 226.0,
    "pct3ResTime" : 226.0,
    "throughput" : 0.13436044428520244,
    "receivedKBytesPerSec" : 0.0914543258464708,
    "sentKBytesPerSec" : 0.07951409105159442
  },
  "getQuerySummary" : {
    "transaction" : "getQuerySummary",
    "sampleCount" : 3,
    "errorCount" : 0,
    "errorPct" : 0.0,
    "meanResTime" : 457.0,
    "minResTime" : 448.0,
    "maxResTime" : 465.0,
    "pct1ResTime" : 465.0,
    "pct2ResTime" : 465.0,
    "pct3ResTime" : 465.0,
    "throughput" : 0.132890365448505,
    "receivedKBytesPerSec" : 0.06255191029900332,
    "sentKBytesPerSec" : 0.09032392026578073
  },
  "Total" : {
    "transaction" : "Total",
    "sampleCount" : 52,
    "errorCount" : 0,
    "errorPct" : 0.0,
    "meanResTime" : 367.84615384615387,
    "minResTime" : 24.0,
    "maxResTime" : 1573.0,
    "pct1ResTime" : 623.4,
    "pct2ResTime" : 1042.6999999999962,
    "pct3ResTime" : 1573.0,
    "throughput" : 1.483975913929397,
    "receivedKBytesPerSec" : 2.2291688218800836,
    "sentKBytesPerSec" : 1.5984065986986675
  },
  "getScoredTransactionSummaryByEnteredBy" : {
    "transaction" : "getScoredTransactionSummaryByEnteredBy",
    "sampleCount" : 3,
    "errorCount" : 0,
    "errorPct" : 0.0,
    "meanResTime" : 325.0,
    "minResTime" : 286.0,
    "maxResTime" : 368.0,
    "pct1ResTime" : 368.0,
    "pct2ResTime" : 368.0,
    "pct3ResTime" : 368.0,
    "throughput" : 0.1338986833296139,
    "receivedKBytesPerSec" : 0.0934937095514394,
    "sentKBytesPerSec" : 0.09401675128319571
  },
  "getLookupList - JOURNAL" : {
    "transaction" : "getLookupList - JOURNAL",
    "sampleCount" : 3,
    "errorCount" : 0,
    "errorPct" : 0.0,
    "meanResTime" : 471.6666666666667,
    "minResTime" : 467.0,
    "maxResTime" : 476.0,
    "pct1ResTime" : 476.0,
    "pct2ResTime" : 476.0,
    "pct3ResTime" : 476.0,
    "throughput" : 0.13289625232568442,
    "receivedKBytesPerSec" : 0.07137982302649065,
    "sentKBytesPerSec" : 0.08331972069637636
  },
  "getScoredTransactionSummaryByRiskLevel - Second call" : {
    "transaction" : "getScoredTransactionSummaryByRiskLevel - Second call",
    "sampleCount" : 3,
    "errorCount" : 0,
    "errorPct" : 0.0,
    "meanResTime" : 277.3333333333333,
    "minResTime" : 201.0,
    "maxResTime" : 316.0,
    "pct1ResTime" : 316.0,
    "pct2ResTime" : 316.0,
    "pct3ResTime" : 316.0,
    "throughput" : 0.1337852301105958,
    "receivedKBytesPerSec" : 0.054088950454869784,
    "sentKBytesPerSec" : 0.09393709028273278
  },
  "getScoredTransactionSummaryByRiskLevel" : {
    "transaction" : "getScoredTransactionSummaryByRiskLevel",
    "sampleCount" : 3,
    "errorCount" : 0,
    "errorPct" : 0.0,
    "meanResTime" : 293.0,
    "minResTime" : 270.0,
    "maxResTime" : 307.0,
    "pct1ResTime" : 307.0,
    "pct2ResTime" : 307.0,
    "pct3ResTime" : 307.0,
    "throughput" : 0.13386283521484987,
    "receivedKBytesPerSec" : 0.054120325956003745,
    "sentKBytesPerSec" : 0.0939915805854268
  },
  "getDatasetMetadata" : {
    "transaction" : "getDatasetMetadata",
    "sampleCount" : 3,
    "errorCount" : 0,
    "errorPct" : 0.0,
    "meanResTime" : 163.0,
    "minResTime" : 42.0,
    "maxResTime" : 405.0,
    "pct1ResTime" : 405.0,
    "pct2ResTime" : 405.0,
    "pct3ResTime" : 405.0,
    "throughput" : 0.13135426244581636,
    "receivedKBytesPerSec" : 0.06760126592670433,
    "sentKBytesPerSec" : 0.07516952909496914
  },
  "(Parent) {Results Page Widget} Data-aggregator APIs" : {
    "transaction" : "(Parent) {Results Page Widget} Data-aggregator APIs",
    "sampleCount" : 3,
    "errorCount" : 0,
    "errorPct" : 0.0,
    "meanResTime" : 614.3333333333334,
    "minResTime" : 581.0,
    "maxResTime" : 638.0,
    "pct1ResTime" : 638.0,
    "pct2ResTime" : 638.0,
    "pct3ResTime" : 638.0,
    "throughput" : 0.13189132155104194,
    "receivedKBytesPerSec" : 1.4376239915809375,
    "sentKBytesPerSec" : 1.0516529692033765
  }
}